langchain_payman_tool/__init__.py
langchain_payman_tool/py.typed
langchain_payman_tool/tools.py
langchain_payman_tool-0.1.3.dist-info/LICENSE
langchain_payman_tool-0.1.3.dist-info/METADATA
langchain_payman_tool-0.1.3.dist-info/WHEEL
langchain_payman_tool-0.1.3.dist-info/RECORD
